{
  "_fv": 79,
  "_type": "recipe",
  "definition": {
    "recipeType": "Crafting",
    "recipeRetstackSize": 2,
    "group": "",
    "unlockingItems": [
      {
        "value": "CUSTOM:SteelIngot"
      }
    ],
    "cookingBookCategory": "MISC",
    "xpReward": 0.0,
    "cookingTime": 200,
    "craftingBookCategory": "MISC",
    "recipeShapeless": false,
    "recipeSlots": [
      {
        "value": ""
      },
      {
        "value": "CUSTOM:SteelIngot"
      },
      {
        "value": ""
      },
      {
        "value": "Blocks.COAL_BLOCK"
      },
      {
        "value": "CUSTOM:SteelPlate"
      },
      {
        "value": "Blocks.COAL_BLOCK"
      },
      {
        "value": ""
      },
      {
        "value": "CUSTOM:SteelIngot"
      },
      {
        "value": ""
      }
    ],
    "recipeReturnStack": {
      "value": "CUSTOM:NobleSteel"
    },
    "name": "noble_ingot_recipe",
    "namespace": "mod"
  }
}