{
  "_fv": 79,
  "_type": "recipe",
  "definition": {
    "recipeType": "Crafting",
    "recipeRetstackSize": 1,
    "group": "",
    "unlockingItems": [
      {
        "value": "CUSTOM:XochitlIngot"
      }
    ],
    "cookingBookCategory": "MISC",
    "xpReward": 0.0,
    "cookingTime": 200,
    "craftingBookCategory": "MISC",
    "recipeShapeless": false,
    "recipeSlots": [
      {
        "value": "CUSTOM:XochitlIngot"
      },
      {
        "value": ""
      },
      {
        "value": "CUSTOM:XochitlIngot"
      },
      {
        "value": "CUSTOM:XochitlIngot"
      },
      {
        "value": "CUSTOM:SoulIngot"
      },
      {
        "value": "CUSTOM:XochitlIngot"
      },
      {
        "value": "CUSTOM:XochitlIngot"
      },
      {
        "value": "CUSTOM:XochitlIngot"
      },
      {
        "value": "CUSTOM:XochitlIngot"
      }
    ],
    "recipeReturnStack": {
      "value": "CUSTOM:XochitlArmor.body"
    },
    "name": "xochitl_chest",
    "namespace": "mod"
  }
}