{
  "display": {
    "icon": {
      "id": "mythicrealms:barrier_magic_book"
    },
    "title": {
      "translate": "advancements.magic_armor_magic_unlock.title"
    },
    "description": {
      "translate": "advancements.magic_armor_magic_unlock.descr"
    },
    "frame": "task",
    "show_toast": true,
    "announce_to_chat": true,
    "hidden": false
  },
  "criteria": {
    "magic_armor_magic_unlock_0": {
      "trigger": "minecraft:consume_item",
      "conditions": {
        "item": {
          "items": [
            "mythicrealms:magic_armor_magic_book"
          ]
        }
      }
    }
  },
  "parent": "mythicrealms:magic_armor_magic_unlock"
}